{
  "minigame": {
    "type": "deathmatch"
  },
  "playerSettings": {
    "controlledObject": false,
    "rightHand": "pistol"
  },
  "spawnPoints": [
    [0, 1, 0],
    [-11, 1, 4],
    [0, 1, -6]
  ],
  "gameObjects": [
    {
      "type": "box",
      "name": "ground",
      "position": { "x": 0, "y": -0.5, "z": 0 },
      "quaternion": { "x": 0, "y": 0, "z": 0, "w": 1 },
      "scale": { "x": 5000, "y": 0.1, "z": 5000 }
    },
    {
      "type": "trimesh",
      "name": "arena",
      "position": { "x": 0, "y": 0, "z": 0 },
      "quaternion": { "x": 0, "y": 0, "z": 0, "w": 1 }
    },
    {
      "type": "spawner",
      "name": "npc_spawner",
      "delay": 1000,
      "maxNumSpawn": 1,
      "spawnerType": "npc"
    }
  ]
}
